LICENSE
README.md
setup.cfg
setup.py
lasertools_rffthelper/__init__.py
lasertools_rffthelper/axes.py
lasertools_rffthelper/envelope.py
lasertools_rffthelper/fft.py
lasertools_rffthelper/shift.py
lasertools_rffthelper.egg-info/PKG-INFO
lasertools_rffthelper.egg-info/SOURCES.txt
lasertools_rffthelper.egg-info/dependency_links.txt
lasertools_rffthelper.egg-info/requires.txt
lasertools_rffthelper.egg-info/top_level.txt